predsim.py
predsim-0.7.0.dist-info/LICENSE.txt
predsim-0.7.0.dist-info/METADATA
predsim-0.7.0.dist-info/WHEEL
predsim-0.7.0.dist-info/entry_points.txt
predsim-0.7.0.dist-info/top_level.txt
predsim-0.7.0.dist-info/RECORD
