Metadata-Version: 2.1
Name: predsim
Version: 0.7.0
Summary: Command-line tool for simulating predictive datasets from MrBayes' output.
Home-page: https://github.com/jmenglund/predsim
Author: Markus Englund
Author-email: jan.markus.englund@gmail.com
License: MIT
Keywords: simulation,predictive,Seq-Gen,DendroPy,MrBayes,phylogenetics,dna-sequences,Bayesian
Platform: UNKNOWN
Classifier: Development Status :: 5 - Production/Stable
Classifier: Intended Audience :: Science/Research
Classifier: License :: OSI Approved :: MIT License
Classifier: Operating System :: OS Independent
Classifier: Programming Language :: Python
Classifier: Programming Language :: Python :: 3
Classifier: Programming Language :: Python :: 3.3
Classifier: Programming Language :: Python :: 3.4
Classifier: Programming Language :: Python :: 3.5
Classifier: Programming Language :: Python :: 3.6
Requires-Dist: dendropy (>=4.0)
